{
  "type": "tabs",
  "items": {
    "general": {
      "type": "panel",
      "label": "ALLGEMEIN",
      "items": {}
    },
    "sensors": {
      "type": "panel",
      "label": "SENSOREN",
      "items": {}
    },
    "actors": {
      "type": "panel",
      "label": "AKTOREN",
      "items": {}
    },
    "ph": {
      "type": "panel",
      "label": "PH-DOSIERUNG",
      "items": {}
    },
    "chlor": {
      "type": "panel",
      "label": "CHLORINATOR",
      "items": {}
    },
    "pump": {
      "type": "panel",
      "label": "PUMPE",
      "items": {}
    },
    "heat": {
      "type": "panel",
      "label": "W\u00c4RMEPUMPE",
      "items": {}
    }
  }
}